deploymodel/__init__.py
deploymodel/docker_utils.py
deploymodel/io/__init__.py
deploymodel/main.py
deploymodel/serverless/__init__.py
deploymodel/set_env.py
deploymodel/settings.py
deploymodel-0.1.32.dist-info/METADATA
deploymodel-0.1.32.dist-info/WHEEL
deploymodel-0.1.32.dist-info/entry_points.txt
deploymodel-0.1.32.dist-info/RECORD
